{
  "composition": {
    "composable": true,
    "composition_notes": "Atomic string block, composable with standard types",
    "conflicts_with": [],
    "input_compatible_types": [
      "arithmetic",
      "string",
      "collection",
      "utility"
    ],
    "output_compatible_types": [
      "arithmetic",
      "string",
      "collection",
      "validation",
      "utility"
    ],
    "requires_blocks": []
  },
  "constraints": {
    "deterministic": true,
    "io_operations": [
      "none"
    ],
    "max_execution_time_ms": null,
    "max_memory_bytes": null,
    "purity": "pure",
    "side_effects": [],
    "thread_safe": true
  },
  "failure_modes": {
    "can_fail": false,
    "error_conditions": [
      "Invalid input types",
      "None values when not allowed"
    ],
    "failure_mode": "never",
    "possible_exceptions": [
      "Exception"
    ],
    "recovery_hints": [
      "Validate inputs before calling",
      "Handle exceptions appropriately"
    ]
  },
  "identity": {
    "algorithm": "sha256",
    "hash_value": "0a4628a9aa5743bac609ed20ac1b077d6ede1d942f2afd33be5e0f8f6a344195",
    "semantic_fingerprint": "073b58eb11fc24deaaae9a3d0b2b53f87ad3e63a927d777bd9e5216dd0843f33",
    "version": "1.0.0"
  },
  "interface": {
    "description": "Format file size in human-readable form.",
    "inputs": [
      {
        "data_type": "integer",
        "default_value": null,
        "description": "Parameter bytes_count",
        "name": "bytes_count",
        "optional": false
      }
    ],
    "outputs": [
      {
        "data_type": "string",
        "default_value": null,
        "description": "Return value of format_file_size",
        "name": "result",
        "optional": false
      }
    ]
  },
  "logic": "def format_file_size(bytes_count: int) -> str:\n    \"\"\"Format file size in human-readable form.\"\"\"\n    units = [\"B\", \"KB\", \"MB\", \"GB\", \"TB\"]\n    size = float(bytes_count)\n    unit_index = 0\n    while size >= 1024 and unit_index < len(units) - 1:\n        size /= 1024\n        unit_index += 1\n    if unit_index == 0:\n        return f\"{int(size)} {units[unit_index]}\"\n    return f\"{size:.1f} {units[unit_index]}\"",
  "metadata": {
    "category": "string",
    "created_at": "2026-01-10T17:49:45.437002+00:00",
    "description": "Format file size in human-readable form.",
    "intent": "Format file size in human-readable form.",
    "language": "python",
    "name": "format_file_size",
    "source_file": "neurop_forge/sources/file_utilities.py",
    "source_line_end": 151,
    "source_line_start": 141,
    "tags": [
      "bytes_count",
      "file",
      "format",
      "size",
      "string_manipulation"
    ],
    "version": "1.0.0"
  },
  "ownership": {
    "attribution_required": true,
    "license_type": "MIT",
    "license_url": null,
    "modifications_allowed": true,
    "original_author": "Lourens Wasserman",
    "original_repository": "neurop-block-forge"
  },
  "sealed": true,
  "trust_score": {
    "determinism_score": 1.0,
    "execution_count": 0,
    "failure_count": 0,
    "last_verified": "2026-01-10T17:49:45.437023+00:00",
    "license_score": 1.0,
    "overall_score": 0.3775,
    "risk_factors": [],
    "risk_level": "low",
    "static_analysis_score": 0.85,
    "success_count": 0,
    "success_rate": 0.0,
    "test_coverage_score": 0.0
  },
  "validation_rules": {
    "input_validators": [
      "type(bytes_count) == integer",
      "bytes_count is not None"
    ],
    "invariants": [],
    "output_validators": [
      "type(result) == string"
    ],
    "postconditions": [
      "type(result) == string"
    ],
    "preconditions": [
      "type(bytes_count) == integer",
      "bytes_count is not None"
    ]
  }
}