{
  "composition": {
    "composable": true,
    "composition_notes": "Atomic aggregation block, composable with standard types",
    "conflicts_with": [],
    "input_compatible_types": [
      "arithmetic",
      "string",
      "collection",
      "utility"
    ],
    "output_compatible_types": [
      "arithmetic",
      "string",
      "collection",
      "validation",
      "utility"
    ],
    "requires_blocks": []
  },
  "constraints": {
    "deterministic": true,
    "io_operations": [
      "none"
    ],
    "max_execution_time_ms": null,
    "max_memory_bytes": null,
    "purity": "pure",
    "side_effects": [],
    "thread_safe": true
  },
  "failure_modes": {
    "can_fail": false,
    "error_conditions": [
      "Invalid input types",
      "None values when not allowed"
    ],
    "failure_mode": "never",
    "possible_exceptions": [
      "Exception"
    ],
    "recovery_hints": [
      "Validate inputs before calling",
      "Handle exceptions appropriately"
    ]
  },
  "identity": {
    "algorithm": "sha256",
    "hash_value": "7301bc4f3b15ebab86e94930d0019ebe3bdfa790da3ffc731df1036c597a22d9",
    "semantic_fingerprint": "a14c3c20b6d416bd02e266ee57f7a6654afbab06a12238f81b6de3de8f9fe74f",
    "version": "1.0.0"
  },
  "interface": {
    "description": "Count the number of vowels in text.",
    "inputs": [
      {
        "data_type": "string",
        "default_value": null,
        "description": "Parameter text",
        "name": "text",
        "optional": false
      }
    ],
    "outputs": [
      {
        "data_type": "integer",
        "default_value": null,
        "description": "Return value of count_vowels",
        "name": "result",
        "optional": false
      }
    ]
  },
  "logic": "def count_vowels(text: str) -> int:\n    \"\"\"Count the number of vowels in text.\"\"\"\n    if not text:\n        return 0\n    vowels = 'aeiouAEIOU'\n    return sum(1 for c in text if c in vowels)",
  "metadata": {
    "category": "aggregation",
    "created_at": "2026-01-10T02:18:42.968707+00:00",
    "description": "Count the number of vowels in text.",
    "intent": "Count the number of vowels in text.",
    "language": "python",
    "name": "count_vowels",
    "source_file": "neurop_forge/sources/text_analysis.py",
    "source_line_end": 236,
    "source_line_start": 231,
    "tags": [
      "aggregation",
      "count",
      "text",
      "vowels"
    ],
    "version": "1.0.0"
  },
  "ownership": {
    "attribution_required": true,
    "license_type": "MIT",
    "license_url": null,
    "modifications_allowed": true,
    "original_author": "Lourens Wasserman",
    "original_repository": "neurop-block-forge"
  },
  "sealed": true,
  "trust_score": {
    "determinism_score": 1.0,
    "last_verified": "2026-01-10T02:18:42.968731+00:00",
    "license_score": 1.0,
    "overall_score": 0.385,
    "risk_factors": [],
    "risk_level": "low",
    "static_analysis_score": 0.9,
    "test_coverage_score": 0.0
  },
  "validation_rules": {
    "input_validators": [
      "type(text) == string",
      "text is not None"
    ],
    "invariants": [],
    "output_validators": [
      "type(result) == integer"
    ],
    "postconditions": [
      "type(result) == integer"
    ],
    "preconditions": [
      "type(text) == string",
      "text is not None"
    ]
  }
}