{
  "composition": {
    "composable": true,
    "composition_notes": "Atomic filtering block, composable with standard types",
    "conflicts_with": [],
    "input_compatible_types": [
      "arithmetic",
      "string",
      "collection",
      "utility"
    ],
    "output_compatible_types": [
      "arithmetic",
      "string",
      "collection",
      "validation",
      "utility"
    ],
    "requires_blocks": []
  },
  "constraints": {
    "deterministic": true,
    "io_operations": [
      "none"
    ],
    "max_execution_time_ms": null,
    "max_memory_bytes": null,
    "purity": "pure",
    "side_effects": [],
    "thread_safe": true
  },
  "failure_modes": {
    "can_fail": false,
    "error_conditions": [
      "Invalid input types",
      "None values when not allowed"
    ],
    "failure_mode": "never",
    "possible_exceptions": [
      "Exception"
    ],
    "recovery_hints": [
      "Validate inputs before calling",
      "Handle exceptions appropriately"
    ]
  },
  "identity": {
    "algorithm": "sha256",
    "hash_value": "8d0d690034edc3b2805f75307f49e87d5677c8f296a2f724743c0fe1c059f6c4",
    "semantic_fingerprint": "68c21f9b301898e22edd575d3f106b81cbea38c14e515893af4ed4f319ef1ce5",
    "version": "1.0.0"
  },
  "interface": {
    "description": "Get parameter value.",
    "inputs": [
      {
        "data_type": "string",
        "default_value": null,
        "description": "Parameter query",
        "name": "query",
        "optional": false
      },
      {
        "data_type": "string",
        "default_value": null,
        "description": "Parameter key",
        "name": "key",
        "optional": false
      },
      {
        "data_type": "string",
        "default_value": null,
        "description": "Parameter default",
        "name": "default",
        "optional": false
      }
    ],
    "outputs": [
      {
        "data_type": "string",
        "default_value": null,
        "description": "Return value of get_param",
        "name": "result",
        "optional": false
      }
    ]
  },
  "logic": "def get_param(v0: str, v1: str, v2: str) -> str:\n    v3 = v4(v0)\n    return v3.get(v1, v2)",
  "metadata": {
    "category": "filtering",
    "created_at": "2026-01-10T00:40:57.217467+00:00",
    "description": "Get parameter value.",
    "intent": "Get parameter value.",
    "language": "python",
    "name": "get_param",
    "source_file": "neurop_forge/sources/query_string.py",
    "source_line_end": 69,
    "source_line_start": 66,
    "tags": [
      "default",
      "filtering",
      "get",
      "key",
      "param",
      "query"
    ],
    "version": "1.0.0"
  },
  "ownership": {
    "attribution_required": true,
    "license_type": "MIT",
    "license_url": null,
    "modifications_allowed": true,
    "original_author": "Lourens Wasserman",
    "original_repository": "neurop-block-forge"
  },
  "sealed": true,
  "trust_score": {
    "determinism_score": 1.0,
    "last_verified": "2026-01-10T00:40:57.217483+00:00",
    "license_score": 1.0,
    "overall_score": 0.355,
    "risk_factors": [],
    "risk_level": "low",
    "static_analysis_score": 0.7,
    "test_coverage_score": 0.0
  },
  "validation_rules": {
    "input_validators": [
      "type(query) == string",
      "query is not None",
      "type(key) == string",
      "key is not None",
      "type(default) == string",
      "default is not None"
    ],
    "invariants": [],
    "output_validators": [
      "type(result) == string"
    ],
    "postconditions": [
      "type(result) == string"
    ],
    "preconditions": [
      "type(query) == string",
      "query is not None",
      "type(key) == string",
      "key is not None",
      "type(default) == string",
      "default is not None"
    ]
  }
}