{
  "composition": {
    "composable": true,
    "composition_notes": "Atomic validation block, composable with standard types",
    "conflicts_with": [],
    "input_compatible_types": [
      "arithmetic",
      "string",
      "collection",
      "utility"
    ],
    "output_compatible_types": [
      "arithmetic",
      "string",
      "collection",
      "validation",
      "utility"
    ],
    "requires_blocks": []
  },
  "constraints": {
    "deterministic": true,
    "io_operations": [
      "none"
    ],
    "max_execution_time_ms": null,
    "max_memory_bytes": null,
    "purity": "pure",
    "side_effects": [],
    "thread_safe": true
  },
  "failure_modes": {
    "can_fail": false,
    "error_conditions": [
      "Invalid input types",
      "None values when not allowed"
    ],
    "failure_mode": "never",
    "possible_exceptions": [
      "Exception"
    ],
    "recovery_hints": [
      "Validate inputs before calling",
      "Handle exceptions appropriately"
    ]
  },
  "identity": {
    "algorithm": "sha256",
    "hash_value": "5ad30550a878266c85a37c163ff18bccef9d566745826aaef6e57809e1aa8e9a",
    "semantic_fingerprint": "a0cf86ce43aa9c803e3cb96035d2d768c7c18bdf4a3665160b4e6396230bedbb",
    "version": "1.0.0"
  },
  "interface": {
    "description": "Check if character is ASCII.",
    "inputs": [
      {
        "data_type": "string",
        "default_value": null,
        "description": "Parameter char",
        "name": "char",
        "optional": false
      }
    ],
    "outputs": [
      {
        "data_type": "boolean",
        "default_value": null,
        "description": "Return value of is_ascii",
        "name": "result",
        "optional": false
      }
    ]
  },
  "logic": "def is_ascii(char: str) -> bool:\n    \"\"\"Check if character is ASCII.\"\"\"\n    return ord(char) < 128",
  "metadata": {
    "category": "validation",
    "created_at": "2026-01-10T12:22:33.509521+00:00",
    "description": "Check if character is ASCII.",
    "intent": "Check if character is ASCII.",
    "language": "python",
    "name": "is_ascii",
    "source_file": "neurop_forge/sources/ascii_utilities.py",
    "source_line_end": 14,
    "source_line_start": 12,
    "tags": [
      "ascii",
      "char",
      "validation"
    ],
    "version": "1.0.0"
  },
  "ownership": {
    "attribution_required": true,
    "license_type": "MIT",
    "license_url": null,
    "modifications_allowed": true,
    "original_author": "Lourens Wasserman",
    "original_repository": "neurop-block-forge"
  },
  "sealed": true,
  "trust_score": {
    "determinism_score": 1.0,
    "execution_count": 0,
    "failure_count": 0,
    "last_verified": "2026-01-10T12:22:33.509539+00:00",
    "license_score": 1.0,
    "overall_score": 0.385,
    "risk_factors": [],
    "risk_level": "low",
    "static_analysis_score": 0.9,
    "success_count": 0,
    "success_rate": 0.0,
    "test_coverage_score": 0.0
  },
  "validation_rules": {
    "input_validators": [
      "type(char) == string",
      "char is not None"
    ],
    "invariants": [],
    "output_validators": [
      "type(result) == boolean"
    ],
    "postconditions": [
      "type(result) == boolean"
    ],
    "preconditions": [
      "type(char) == string",
      "char is not None"
    ]
  }
}