{
  "composition": {
    "composable": true,
    "composition_notes": "Atomic collection block, composable with standard types",
    "conflicts_with": [],
    "input_compatible_types": [
      "arithmetic",
      "string",
      "collection",
      "utility"
    ],
    "output_compatible_types": [
      "arithmetic",
      "string",
      "collection",
      "validation",
      "utility"
    ],
    "requires_blocks": []
  },
  "constraints": {
    "deterministic": true,
    "io_operations": [
      "none"
    ],
    "max_execution_time_ms": null,
    "max_memory_bytes": null,
    "purity": "pure",
    "side_effects": [],
    "thread_safe": true
  },
  "failure_modes": {
    "can_fail": false,
    "error_conditions": [
      "Invalid input types",
      "None values when not allowed"
    ],
    "failure_mode": "never",
    "possible_exceptions": [
      "Exception"
    ],
    "recovery_hints": [
      "Validate inputs before calling",
      "Handle exceptions appropriately"
    ]
  },
  "identity": {
    "algorithm": "sha256",
    "hash_value": "a5d372f62b7e1f153eb5c878ff0daa4cabebaa705b4e26f86f8501d06af37d6b",
    "semantic_fingerprint": "7908c7cd7ab5163dc827351b68e58c5c950157efa92b15fe09dc0640e573b588",
    "version": "1.0.0"
  },
  "interface": {
    "description": "Create user object.",
    "inputs": [
      {
        "data_type": "string",
        "default_value": null,
        "description": "Parameter user_id",
        "name": "user_id",
        "optional": false
      },
      {
        "data_type": "string",
        "default_value": null,
        "description": "Parameter email",
        "name": "email",
        "optional": false
      },
      {
        "data_type": "integer",
        "default_value": null,
        "description": "Parameter created_at",
        "name": "created_at",
        "optional": false
      }
    ],
    "outputs": [
      {
        "data_type": "dict",
        "default_value": null,
        "description": "Return value of create_user",
        "name": "result",
        "optional": false
      }
    ]
  },
  "logic": "def create_user(user_id: str, email: str, created_at: int) -> dict:\n    \"\"\"Create user object.\"\"\"\n    return {\n        \"user_id\": user_id,\n        \"email\": email,\n        \"created_at\": created_at,\n        \"active\": True,\n        \"verified\": False,\n        \"roles\": []\n    }",
  "metadata": {
    "category": "collection",
    "created_at": "2026-01-10T12:22:34.702696+00:00",
    "description": "Create user object.",
    "intent": "Create user object.",
    "language": "python",
    "name": "create_user",
    "source_file": "neurop_forge/sources/user_utilities.py",
    "source_line_end": 25,
    "source_line_start": 16,
    "tags": [
      "create",
      "created_at",
      "dict_operation",
      "email",
      "user",
      "user_id"
    ],
    "version": "1.0.0"
  },
  "ownership": {
    "attribution_required": true,
    "license_type": "MIT",
    "license_url": null,
    "modifications_allowed": true,
    "original_author": "Lourens Wasserman",
    "original_repository": "neurop-block-forge"
  },
  "sealed": true,
  "trust_score": {
    "determinism_score": 1.0,
    "execution_count": 0,
    "failure_count": 0,
    "last_verified": "2026-01-10T12:22:34.702722+00:00",
    "license_score": 1.0,
    "overall_score": 0.33999999999999997,
    "risk_factors": [],
    "risk_level": "low",
    "static_analysis_score": 0.6,
    "success_count": 0,
    "success_rate": 0.0,
    "test_coverage_score": 0.0
  },
  "validation_rules": {
    "input_validators": [
      "type(user_id) == string",
      "user_id is not None",
      "type(email) == string",
      "email is not None",
      "type(created_at) == integer",
      "created_at is not None"
    ],
    "invariants": [],
    "output_validators": [
      "type(result) == dict"
    ],
    "postconditions": [
      "type(result) == dict"
    ],
    "preconditions": [
      "type(user_id) == string",
      "user_id is not None",
      "type(email) == string",
      "email is not None",
      "type(created_at) == integer",
      "created_at is not None"
    ]
  }
}