{
  "composition": {
    "composable": true,
    "composition_notes": "Atomic string block, composable with standard types",
    "conflicts_with": [],
    "input_compatible_types": [
      "arithmetic",
      "string",
      "collection",
      "utility"
    ],
    "output_compatible_types": [
      "arithmetic",
      "string",
      "collection",
      "validation",
      "utility"
    ],
    "requires_blocks": []
  },
  "constraints": {
    "deterministic": true,
    "io_operations": [
      "none"
    ],
    "max_execution_time_ms": null,
    "max_memory_bytes": null,
    "purity": "pure",
    "side_effects": [],
    "thread_safe": true
  },
  "failure_modes": {
    "can_fail": false,
    "error_conditions": [
      "Invalid input types",
      "None values when not allowed"
    ],
    "failure_mode": "never",
    "possible_exceptions": [
      "Exception"
    ],
    "recovery_hints": [
      "Validate inputs before calling",
      "Handle exceptions appropriately"
    ]
  },
  "identity": {
    "algorithm": "sha256",
    "hash_value": "c0434def881a388a89a0172b2a7885cc1e90c8ce29b83f786a642688a69350e5",
    "semantic_fingerprint": "d0f057652c93485817e1b27a6c67f6ee52aeda4eafcf432d22430c4f791afe41",
    "version": "1.0.0"
  },
  "interface": {
    "description": "URL decode a string.",
    "inputs": [
      {
        "data_type": "string",
        "default_value": null,
        "description": "Parameter encoded",
        "name": "encoded",
        "optional": false
      }
    ],
    "outputs": [
      {
        "data_type": "string",
        "default_value": null,
        "description": "Return value of url_decode",
        "name": "result",
        "optional": false
      }
    ]
  },
  "logic": "def url_decode(encoded: str) -> str:\n    \"\"\"URL decode a string.\"\"\"\n    from urllib.parse import unquote\n    return unquote(encoded)",
  "metadata": {
    "category": "string",
    "created_at": "2026-01-10T12:22:32.221897+00:00",
    "description": "URL decode a string.",
    "intent": "URL decode a string.",
    "language": "python",
    "name": "url_decode",
    "source_file": "neurop_forge/sources/encoding_schemes.py",
    "source_line_end": 58,
    "source_line_start": 55,
    "tags": [
      "decode",
      "encoded",
      "string_manipulation",
      "url"
    ],
    "version": "1.0.0"
  },
  "ownership": {
    "attribution_required": true,
    "license_type": "MIT",
    "license_url": null,
    "modifications_allowed": true,
    "original_author": "Lourens Wasserman",
    "original_repository": "neurop-block-forge"
  },
  "sealed": true,
  "trust_score": {
    "determinism_score": 1.0,
    "execution_count": 0,
    "failure_count": 0,
    "last_verified": "2026-01-10T12:22:32.221925+00:00",
    "license_score": 1.0,
    "overall_score": 0.33999999999999997,
    "risk_factors": [],
    "risk_level": "low",
    "static_analysis_score": 0.6,
    "success_count": 0,
    "success_rate": 0.0,
    "test_coverage_score": 0.0
  },
  "validation_rules": {
    "input_validators": [
      "type(encoded) == string",
      "encoded is not None"
    ],
    "invariants": [],
    "output_validators": [
      "type(result) == string"
    ],
    "postconditions": [
      "type(result) == string"
    ],
    "preconditions": [
      "type(encoded) == string",
      "encoded is not None"
    ]
  }
}